Workbook

Sheet Resumen_Gobierno_TI
A1: Mes | B1: Año | C1: Área responsable | D1: Nivel de madurez de gobierno de TI | E1: Porcentaje de cumplimiento de políticas | F1: Porcentaje de cumplimiento normativo | G1: Índice de satisfacción de usuarios | H1: Estado general del gobierno de TI
A2: Enero | B2: 2025 | C2: Oficina de Gobierno TI | D2: 2.85 | E2: 0.781 | F2: 0.752 | G2: 0.768 | H2: =IF(AND(D2>=4,E2>=0.9,F2>=0.9,G2>=0.85),"Óptimo",IF(AND(D2>=3,E2>=0.8,F2>=0.8,G2>=0.75),"Controlado","Requiere atención")) -> Requiere atención
A3: Febrero | B3: 2025 | C3: Oficina de Gobierno TI | D3: 2.92 | E3: 0.796 | F3: 0.769 | G3: 0.776 | H3: =IF(AND(D3>=4,E3>=0.9,F3>=0.9,G3>=0.85),"Óptimo",IF(AND(D3>=3,E3>=0.8,F3>=0.8,G3>=0.75),"Controlado","Requiere atención")) -> Requiere atención
A4: Marzo | B4: 2025 | C4: Oficina de Gobierno TI | D4: 3.02 | E4: 0.804 | F4: 0.781 | G4: 0.789 | H4: =IF(AND(D4>=4,E4>=0.9,F4>=0.9,G4>=0.85),"Óptimo",IF(AND(D4>=3,E4>=0.8,F4>=0.8,G4>=0.75),"Controlado","Requiere atención")) -> Requiere atención
A5: Abril | B5: 2025 | C5: Oficina de Gobierno TI | D5: 3.08 | E5: 0.816 | F5: 0.793 | G5: 0.801 | H5: =IF(AND(D5>=4,E5>=0.9,F5>=0.9,G5>=0.85),"Óptimo",IF(AND(D5>=3,E5>=0.8,F5>=0.8,G5>=0.75),"Controlado","Requiere atención")) -> Requiere atención
A6: Mayo | B6: 2025 | C6: Oficina de Gobierno TI | D6: 3.16 | E6: 0.831 | F6: 0.807 | G6: 0.812 | H6: =IF(AND(D6>=4,E6>=0.9,F6>=0.9,G6>=0.85),"Óptimo",IF(AND(D6>=3,E6>=0.8,F6>=0.8,G6>=0.75),"Controlado","Requiere atención")) -> Controlado
A7: Junio | B7: 2025 | C7: Oficina de Gobierno TI | D7: 3.25 | E7: 0.842 | F7: 0.821 | G7: 0.823 | H7: =IF(AND(D7>=4,E7>=0.9,F7>=0.9,G7>=0.85),"Óptimo",IF(AND(D7>=3,E7>=0.8,F7>=0.8,G7>=0.75),"Controlado","Requiere atención")) -> Controlado
A8: Julio | B8: 2025 | C8: Oficina de Gobierno TI | D8: 3.31 | E8: 0.854 | F8: 0.835 | G8: 0.831 | H8: =IF(AND(D8>=4,E8>=0.9,F8>=0.9,G8>=0.85),"Óptimo",IF(AND(D8>=3,E8>=0.8,F8>=0.8,G8>=0.75),"Controlado","Requiere atención")) -> Controlado
A9: Agosto | B9: 2025 | C9: Oficina de Gobierno TI | D9: 3.38 | E9: 0.866 | F9: 0.848 | G9: 0.842 | H9: =IF(AND(D9>=4,E9>=0.9,F9>=0.9,G9>=0.85),"Óptimo",IF(AND(D9>=3,E9>=0.8,F9>=0.8,G9>=0.75),"Controlado","Requiere atención")) -> Controlado
A10: Septiembre | B10: 2025 | C10: Oficina de Gobierno TI | D10: 3.46 | E10: 0.881 | F10: 0.862 | G10: 0.854 | H10: =IF(AND(D10>=4,E10>=0.9,F10>=0.9,G10>=0.85),"Óptimo",IF(AND(D10>=3,E10>=0.8,F10>=0.8,G10>=0.75),"Controlado","Requiere atención")) -> Controlado
A11: Octubre | B11: 2025 | C11: Oficina de Gobierno TI | D11: 3.55 | E11: 0.896 | F11: 0.877 | G11: 0.866 | H11: =IF(AND(D11>=4,E11>=0.9,F11>=0.9,G11>=0.85),"Óptimo",IF(AND(D11>=3,E11>=0.8,F11>=0.8,G11>=0.75),"Controlado","Requiere atención")) -> Controlado
A12: Noviembre | B12: 2025 | C12: Oficina de Gobierno TI | D12: 3.63 | E12: 0.918 | F12: 0.895 | G12: 0.879 | H12: =IF(AND(D12>=4,E12>=0.9,F12>=0.9,G12>=0.85),"Óptimo",IF(AND(D12>=3,E12>=0.8,F12>=0.8,G12>=0.75),"Controlado","Requiere atención")) -> Controlado
A13: Diciembre | B13: 2025 | C13: Oficina de Gobierno TI | D13: 3.72 | E13: 0.934 | F13: 0.912 | G13: 0.891 | H13: =IF(AND(D13>=4,E13>=0.9,F13>=0.9,G13>=0.85),"Óptimo",IF(AND(D13>=3,E13>=0.8,F13>=0.8,G13>=0.75),"Controlado","Requiere atención")) -> Controlado

Sheet Riesgos_TI
A1: ID del riesgo | B1: Categoría del riesgo | C1: Descripción del riesgo | D1: Probabilidad (1-5) | E1: Impacto (1-5) | F1: Nivel de riesgo | G1: Área responsable | H1: Estado del tratamiento | I1: Fecha de identificación | J1: Fecha estimada de mitigación | K1: Puntaje del riesgo
A2: R-001 | B2: Cumplimiento | C2: Incumplimiento de controles regulatorios o políticas internas de TI. | D2: 3 | E2: 4 | F2: =IF(K2>=20,"Crítico",IF(K2>=12,"Alto",IF(K2>=6,"Medio","Bajo"))) -> Alto | G2: Oficina de Gobierno TI | H2: En tratamiento | I2: 45663 | J2: 45772 | K2: =D2*E2 -> 12
A3: R-002 | B3: Ciberseguridad | C3: Acceso no autorizado a información sensible por credenciales comprometidas. | D3: 3 | E3: 4 | F3: =IF(K3>=20,"Crítico",IF(K3>=12,"Alto",IF(K3>=6,"Medio","Bajo"))) -> Alto | G3: Seguridad de la Información | H3: En tratamiento | I3: 45675 | J3: 45797 | K3: =D3*E3 -> 12
A4: R-003 | B4: Ciberseguridad | C4: Acceso no autorizado a información sensible por credenciales comprometidas. | D4: 2 | E4: 2 | F4: =IF(K4>=20,"Crítico",IF(K4>=12,"Alto",IF(K4>=6,"Medio","Bajo"))) -> Bajo | G4: Seguridad de la Información | H4: En seguimiento | I4: 45668 | J4: 45759 | K4: =D4*E4 -> 4
A5: R-004 | B5: Aplicaciones | C5: Vulnerabilidades o fallas funcionales en sistemas institucionales. | D5: 4 | E5: 2 | F5: =IF(K5>=20,"Crítico",IF(K5>=12,"Alto",IF(K5>=6,"Medio","Bajo"))) -> Medio | G5: Desarrollo de Sistemas | H5: En seguimiento | I5: 45698 | J5: 45818 | K5: =D5*E5 -> 8
A6: R-005 | B6: Continuidad | C6: Interrupción prolongada de servicios críticos por falla de infraestructura. | D6: 2 | E6: 5 | F6: =IF(K6>=20,"Crítico",IF(K6>=12,"Alto",IF(K6>=6,"Medio","Bajo"))) -> Medio | G6: Continuidad del Negocio | H6: Cerrado | I6: 45709 | J6: 45795 | K6: =D6*E6 -> 10
A7: R-006 | B7: Proveedores | C7: Dependencia excesiva de un proveedor tecnológico estratégico. | D7: 4 | E7: 3 | F7: =IF(K7>=20,"Crítico",IF(K7>=12,"Alto",IF(K7>=6,"Medio","Bajo"))) -> Alto | G7: Dirección de Tecnología | H7: En tratamiento | I7: 45712 | J7: 45773 | K7: =D7*E7 -> 12
A8: R-007 | B8: Proyectos | C8: Retraso o sobrecosto en iniciativas tecnológicas prioritarias. | D8: 2 | E8: 4 | F8: =IF(K8>=20,"Crítico",IF(K8>=12,"Alto",IF(K8>=6,"Medio","Bajo"))) -> Medio | G8: Gestión de Proyectos TI | H8: Aceptado | I8: 45727 | J8: 45763 | K8: =D8*E8 -> 8
A9: R-008 | B9: Continuidad | C9: Interrupción prolongada de servicios críticos por falla de infraestructura. | D9: 3 | E9: 4 | F9: =IF(K9>=20,"Crítico",IF(K9>=12,"Alto",IF(K9>=6,"Medio","Bajo"))) -> Alto | G9: Continuidad del Negocio | H9: Cerrado | I9: 45726 | J9: 45764 | K9: =D9*E9 -> 12
A10: R-009 | B10: Proveedores | C10: Dependencia excesiva de un proveedor tecnológico estratégico. | D10: 5 | E10: 3 | F10: =IF(K10>=20,"Crítico",IF(K10>=12,"Alto",IF(K10>=6,"Medio","Bajo"))) -> Alto | G10: Dirección de Tecnología | H10: En tratamiento | I10: 45738 | J10: 45863 | K10: =D10*E10 -> 15
A11: R-010 | B11: Proveedores | C11: Dependencia excesiva de un proveedor tecnológico estratégico. | D11: 4 | E11: 3 | F11: =IF(K11>=20,"Crítico",IF(K11>=12,"Alto",IF(K11>=6,"Medio","Bajo"))) -> Alto | G11: Dirección de Tecnología | H11: En tratamiento | I11: 45772 | J11: 45886 | K11: =D11*E11 -> 12
A12: R-011 | B12: Proveedores | C12: Dependencia excesiva de un proveedor tecnológico estratégico. | D12: 3 | E12: 3 | F12: =IF(K12>=20,"Crítico",IF(K12>=12,"Alto",IF(K12>=6,"Medio","Bajo"))) -> Medio | G12: Dirección de Tecnología | H12: Cerrado | I12: 45750 | J12: 45900 | K12: =D12*E12 -> 9
A13: R-012 | B13: Aplicaciones | C13: Vulnerabilidades o fallas funcionales en sistemas institucionales. | D13: 4 | E13: 4 | F13: =IF(K13>=20,"Crítico",IF(K13>=12,"Alto",IF(K13>=6,"Medio","Bajo"))) -> Alto | G13: Desarrollo de Sistemas | H13: Cerrado | I13: 45750 | J13: 45881 | K13: =D13*E13 -> 16
... A37: R-036 | B37: Continuidad | C37: Interrupción prolongada de servicios críticos por falla de infraestructura. | D37: 3 | E37: 3 | F37: =IF(K37>=20,"Crítico",IF(K37>=12,"Alto",IF(K37>=6,"Medio","Bajo"))) -> Medio | G37: Continuidad del Negocio | H37: Cerrado | I37: 46000 | J37: 46146 | K37: =D37*E37 -> 9

Sheet Incidentes_Servicios_TI
A1: ID del incidente | B1: Fecha | C1: Servicio afectado | D1: Tipo de incidente | E1: Prioridad | F1: Tiempo de resolución en horas | G1: Estado | H1: Área responsable | I1: Impacto en usuarios | J1: Causa raíz
A2: INC-0001 | B2: 45670 | C2: Correo institucional | D2: Rendimiento | E2: Crítica | F2: 3.2 | G2: En seguimiento | H2: Infraestructura y Operaciones | I2: Alto | J2: Interrupción del proveedor
A3: INC-0002 | B3: 45658 | C3: Base de datos institucional | D3: Degradación del servicio | E3: Media | F3: 24 | G3: En seguimiento | H3: Infraestructura y Operaciones | I3: Medio | J3: Configuración incorrecta
A4: INC-0003 | B4: 45682 | C4: Red corporativa | D4: Caída total | E4: Media | F4: 5.4 | G4: Cerrado | H4: Infraestructura y Operaciones | I4: Medio | J4: Credenciales o permisos incorrectos
A5: INC-0004 | B5: 45682 | C5: ERP Financiero | D5: Rendimiento | E5: Alta | F5: 14.6 | G5: Resuelto | H5: Desarrollo de Sistemas | I5: Alto | J5: Falla de componente físico
A6: INC-0005 | B6: 45669 | C6: Base de datos institucional | D6: Rendimiento | E6: Baja | F6: 27.2 | G6: Cerrado | H6: Infraestructura y Operaciones | I6: Bajo | J6: Falla de componente físico
A7: INC-0006 | B7: 45661 | C7: Correo institucional | D7: Rendimiento | E7: Media | F7: 15.2 | G7: Cerrado | H7: Infraestructura y Operaciones | I7: Medio | J7: Credenciales o permisos incorrectos
A8: INC-0007 | B8: 45701 | C8: Base de datos institucional | D8: Error de aplicación | E8: Baja | F8: 42.3 | G8: Resuelto | H8: Infraestructura y Operaciones | I8: Bajo | J8: Credenciales o permisos incorrectos
A9: INC-0008 | B9: 45693 | C9: Portal de servicios | D9: Seguridad | E9: Baja | F9: 33.4 | G9: En seguimiento | H9: Desarrollo de Sistemas | I9: Bajo | J9: Interrupción del proveedor
A10: INC-0009 | B10: 45700 | C10: Base de datos institucional | D10: Acceso y autenticación | E10: Media | F10: 19.5 | G10: En seguimiento | H10: Infraestructura y Operaciones | I10: Medio | J10: Falla de componente físico
A11: INC-0010 | B11: 45692 | C11: Gestión documental | D11: Caída total | E11: Media | F11: 27.5 | G11: En seguimiento | H11: Desarrollo de Sistemas | I11: Medio | J11: Interrupción del proveedor
A12: INC-0011 | B12: 45689 | C12: Portal de servicios | D12: Rendimiento | E12: Baja | F12: 18.7 | G12: Resuelto | H12: Desarrollo de Sistemas | I12: Bajo | J12: Saturación de recursos de infraestructura
A13: INC-0012 | B13: 45709 | C13: ERP Financiero | D13: Degradación del servicio | E13: Media | F13: 7.3 | G13: Resuelto | H13: Desarrollo de Sistemas | I13: Medio | J13: Falla de componente físico
... A42: INC-0041 | B42: 45854 | C42: Gestión documental | D42: Caída total | E42: Media | F42: 10.2 | G42: Resuelto | H42: Desarrollo de Sistemas | I42: Medio | J42: Saturación de recursos de infraestructura
A43: INC-0042 | B43: 45844 | C43: Gestión documental | D43: Conectividad | E43: Media | G43: Abierto | H43: Desarrollo de Sistemas | I43: Medio | J43: Cambio no controlado en producción
A44: INC-0043 | B44: 45871 | C44: Portal de servicios | D44: Caída total | E44: Media | F44: 23.2 | G44: Resuelto | H44: Desarrollo de Sistemas | I44: Medio | J44: Falla de componente físico
A45: INC-0044 | B45: 45871 | C45: Gestión documental | D45: Conectividad | E45: Media | F45: 17.1 | G45: Resuelto | H45: Desarrollo de Sistemas | I45: Medio | J45: Actualización pendiente
A46: INC-0045 | B46: 45872 | C46: ERP Financiero | D46: Rendimiento | E46: Media | F46: 6.7 | G46: Resuelto | H46: Desarrollo de Sistemas | I46: Medio | J46: Falla de componente físico
A47: INC-0046 | B47: 45880 | C47: Correo institucional | D47: Error de aplicación | E47: Crítica | F47: 2.5 | G47: Resuelto | H47: Infraestructura y Operaciones | I47: Alto | J47: Interrupción del proveedor
A48: INC-0047 | B48: 45884 | C48: Portal de servicios | D48: Error de aplicación | E48: Media | F48: 10 | G48: Cerrado | H48: Desarrollo de Sistemas | I48: Medio | J48: Credenciales o permisos incorrectos
A49: INC-0048 | B49: 45882 | C49: Gestión documental | D49: Conectividad | E49: Media | F49: 17.1 | G49: Resuelto | H49: Desarrollo de Sistemas | I49: Medio | J49: Configuración incorrecta
A50: INC-0049 | B50: 45922 | C50: ERP Financiero | D50: Conectividad | E50: Baja | F50: 26.2 | G50: En seguimiento | H50: Desarrollo de Sistemas | I50: Bajo | J50: Falla de componente físico
A51: INC-0050 | B51: 45920 | C51: ERP Financiero | D51: Degradación del servicio | E51: Media | F51: 28 | G51: Resuelto | H51: Desarrollo de Sistemas | I51: Medio | J51: Credenciales o permisos incorrectos
A52: INC-0051 | B52: 45909 | C52: Portal de servicios | D52: Error de aplicación | E52: Alta | F52: 3.4 | G52: Resuelto | H52: Desarrollo de Sistemas | I52: Medio | J52: Configuración incorrecta
A53: INC-0052 | B53: 45911 | C53: Correo institucional | D53: Error de aplicación | E53: Baja | F53: 18.3 | G53: Resuelto | H53: Infraestructura y Operaciones | I53: Bajo | J53: Configuración incorrecta
A54: INC-0053 | B54: 45926 | C54: Gestión documental | D54: Seguridad | E54: Media | F54: 19.1 | G54: Cerrado | H54: Desarrollo de Sistemas | I54: Medio | J54: Credenciales o permisos incorrectos
A55: INC-0054 | B55: 45920 | C55: Red corporativa | D55: Acceso y autenticación | E55: Media | F55: 20.5 | G55: Resuelto | H55: Infraestructura y Operaciones | I55: Medio | J55: Falla de componente físico
... A66: INC-0065 | B66: 45975 | C66: Portal de servicios | D66: Error de aplicación | E66: Media | F66: 13.7 | G66: Resuelto | H66: Desarrollo de Sistemas | I66: Medio | J66: Actualización pendiente
A67: INC-0066 | B67: 45989 | C67: Base de datos institucional | D67: Caída total | E67: Baja | G67: Abierto | H67: Infraestructura y Operaciones | I67: Bajo | J67: Cambio no controlado en producción
A68: INC-0067 | B68: 46002 | C68: Red corporativa | D68: Caída total | E68: Media | F68: 26.4 | G68: En seguimiento | H68: Infraestructura y Operaciones | I68: Medio | J68: Error de software
A69: INC-0068 | B69: 46015 | C69: Red corporativa | D69: Error de aplicación | E69: Alta | F69: 12.7 | G69: Cerrado | H69: Infraestructura y Operaciones | I69: Alto | J69: Credenciales o permisos incorrectos
A70: INC-0069 | B70: 46016 | C70: Correo institucional | D70: Error de aplicación | E70: Media | F70: 26 | G70: Resuelto | H70: Infraestructura y Operaciones | I70: Medio | J70: Cambio no controlado en producción
A71: INC-0070 | B71: 45993 | C71: ERP Financiero | D71: Degradación del servicio | E71: Media | F71: 10.4 | G71: En seguimiento | H71: Desarrollo de Sistemas | I71: Medio | J71: Actualización pendiente
A72: INC-0071 | B72: 45996 | C72: ERP Financiero | D72: Rendimiento | E72: Media | F72: 28.1 | G72: Resuelto | H72: Desarrollo de Sistemas | I72: Medio | J72: Actualización pendiente
A73: INC-0072 | B73: 46004 | C73: Portal de servicios | D73: Acceso y autenticación | E73: Baja | F73: 33.7 | G73: Cerrado | H73: Desarrollo de Sistemas | I73: Bajo | J73: Falla de componente físico

Sheet Auditorias_TI
A1: ID de auditoría | B1: Fecha de auditoría | C1: Proceso auditado | D1: Hallazgos críticos | E1: Hallazgos medios | F1: Hallazgos bajos | G1: Porcentaje de cumplimiento | H1: Estado del plan de acción | I1: Responsable | J1: Fecha de cierre estimada
A2: AUD-001 | B2: 45665 | C2: Seguridad de la información | D2: 1 | E2: 6 | F2: 1 | G2: =MAX(0,1-((D2*5+E2*2+F2)/100)) -> 0.82 | H2: En ejecución | I2: Jefe de Seguridad TI | J2: 45774
A3: AUD-002 | B3: 45666 | C3: Gestión de cambios | D3: 0 | E3: 6 | F3: 5 | G3: =MAX(0,1-((D3*5+E3*2+F3)/100)) -> 0.83 | H3: Cerrado | I3: Coordinador de Gobierno TI | J3: 45786
A4: AUD-003 | B4: 45698 | C4: Gestión de proveedores | D4: 0 | E4: 1 | F4: 6 | G4: =MAX(0,1-((D4*5+E4*2+F4)/100)) -> 0.92 | H4: Pendiente | I4: Coordinador de Gobierno TI | J4: 45813
A5: AUD-004 | B5: 45729 | C5: Seguridad de la información | D5: 1 | E5: 4 | F5: 1 | G5: =MAX(0,1-((D5*5+E5*2+F5)/100)) -> 0.86 | H5: En ejecución | I5: Jefe de Seguridad TI | J5: 45815
A6: AUD-005 | B6: 45751 | C6: Continuidad operativa | D6: 0 | E6: 2 | F6: 5 | G6: =MAX(0,1-((D6*5+E6*2+F6)/100)) -> 0.91 | H6: Pendiente | I6: Coordinador de Gobierno TI | J6: 45802
A7: AUD-006 | B7: 45755 | C7: Mesa de servicios | D7: 0 | E7: 1 | F7: 1 | G7: =MAX(0,1-((D7*5+E7*2+F7)/100)) -> 0.97 | H7: En ejecución | I7: Coordinador de Gobierno TI | J7: 45844
A8: AUD-007 | B8: 45782 | C8: Gestión de cambios | D8: 0 | E8: 2 | F8: 6 | G8: =MAX(0,1-((D8*5+E8*2+F8)/100)) -> 0.9 | H8: Pendiente | I8: Jefe de Desarrollo | J8: 45840
A9: AUD-008 | B9: 45826 | C9: Gestión de proveedores | D9: 0 | E9: 6 | F9: 5 | G9: =MAX(0,1-((D9*5+E9*2+F9)/100)) -> 0.83 | H9: Cerrado | I9: Gerente de Servicios TI | J9: 45872
A10: AUD-009 | B10: 45817 | C10: Gobierno y arquitectura de TI | D10: 2 | E10: 3 | F10: 8 | G10: =MAX(0,1-((D10*5+E10*2+F10)/100)) -> 0.76 | H10: En ejecución | I10: Coordinador de Gobierno TI | J10: 45935
A11: AUD-010 | B11: 45853 | C11: Continuidad operativa | D11: 0 | E11: 1 | F11: 1 | G11: =MAX(0,1-((D11*5+E11*2+F11)/100)) -> 0.97 | H11: En ejecución | I11: Gerente de Servicios TI | J11: 45924
A12: AUD-011 | B12: 45893 | C12: Gobierno y arquitectura de TI | D12: 0 | E12: 3 | F12: 4 | G12: =MAX(0,1-((D12*5+E12*2+F12)/100)) -> 0.9 | H12: Pendiente | I12: Jefe de Desarrollo | J12: 45973
A13: AUD-012 | B13: 45871 | C13: Gobierno y arquitectura de TI | D13: 0 | E13: 2 | F13: 1 | G13: =MAX(0,1-((D13*5+E13*2+F13)/100)) -> 0.95 | H13: En ejecución | I13: Gerente de Servicios TI | J13: 45964
... A19: AUD-018 | B19: 45998 | C19: Continuidad operativa | D19: 0 | E19: 3 | F19: 8 | G19: =MAX(0,1-((D19*5+E19*2+F19)/100)) -> 0.86 | H19: Cerrado | I19: Jefe de Desarrollo | J19: 46083

Sheet Disponibilidad_Sistemas
A1: Mes | B1: Sistema o plataforma | C1: Horas programadas | D1: Horas de indisponibilidad | E1: Porcentaje de disponibilidad | F1: Número de interrupciones | G1: SLA comprometido | H1: Cumplimiento del SLA
A2: Enero | B2: ERP Financiero | C2: 744 | D2: 3.47 | E2: =1-(D2/C2) -> 0.99533602 | F2: 2 | G2: 0.997 | H2: =IF(E2>=G2,"Cumple","No cumple") -> No cumple
A3: Enero | B3: Correo institucional | C3: 744 | D3: 2.64 | E3: =1-(D3/C3) -> 0.99645161 | F3: 2 | G3: 0.995 | H3: =IF(E3>=G3,"Cumple","No cumple") -> Cumple
A4: Enero | B4: Portal de servicios | C4: 744 | D4: 5.41 | E4: =1-(D4/C4) -> 0.99272849 | F4: 5 | G4: 0.995 | H4: =IF(E4>=G4,"Cumple","No cumple") -> No cumple
A5: Enero | B5: Red corporativa | C5: 744 | D5: 1.51 | E5: =1-(D5/C5) -> 0.99797043 | F5: 1 | G5: 0.999 | H5: =IF(E5>=G5,"Cumple","No cumple") -> No cumple
A6: Enero | B6: Base de datos institucional | C6: 744 | D6: 0.52 | E6: =1-(D6/C6) -> 0.99930108 | F6: 1 | G6: 0.999 | H6: =IF(E6>=G6,"Cumple","No cumple") -> Cumple
A7: Enero | B7: Gestión documental | C7: 744 | D7: 4.79 | E7: =1-(D7/C7) -> 0.99356183 | F7: 6 | G7: 0.995 | H7: =IF(E7>=G7,"Cumple","No cumple") -> No cumple
A8: Febrero | B8: ERP Financiero | C8: 672 | D8: 3.4 | E8: =1-(D8/C8) -> 0.99494048 | F8: 2 | G8: 0.997 | H8: =IF(E8>=G8,"Cumple","No cumple") -> No cumple
A9: Febrero | B9: Correo institucional | C9: 672 | D9: 4.82 | E9: =1-(D9/C9) -> 0.99282738 | F9: 3 | G9: 0.995 | H9: =IF(E9>=G9,"Cumple","No cumple") -> No cumple
A10: Febrero | B10: Portal de servicios | C10: 672 | D10: 2.87 | E10: =1-(D10/C10) -> 0.99572917 | F10: 4 | G10: 0.995 | H10: =IF(E10>=G10,"Cumple","No cumple") -> Cumple
A11: Febrero | B11: Red corporativa | C11: 672 | D11: 0.96 | E11: =1-(D11/C11) -> 0.99857143 | F11: 1 | G11: 0.999 | H11: =IF(E11>=G11,"Cumple","No cumple") -> No cumple
A12: Febrero | B12: Base de datos institucional | C12: 672 | D12: 0.94 | E12: =1-(D12/C12) -> 0.99860119 | F12: 1 | G12: 0.999 | H12: =IF(E12>=G12,"Cumple","No cumple") -> No cumple
A13: Febrero | B13: Gestión documental | C13: 672 | D13: 2.64 | E13: =1-(D13/C13) -> 0.99607143 | F13: 3 | G13: 0.995 | H13: =IF(E13>=G13,"Cumple","No cumple") -> Cumple
... A73: Diciembre | B73: Gestión documental | C73: 744 | D73: 3.95 | E73: =1-(D73/C73) -> 0.99469086 | F73: 3 | G73: 0.995 | H73: =IF(E73>=G73,"Cumple","No cumple") -> No cumple

Sheet Proyectos_TI
A1: ID del proyecto | B1: Nombre del proyecto | C1: Categoría | D1: Presupuesto aprobado | E1: Presupuesto ejecutado | F1: Porcentaje de ejecución presupuestaria | G1: Porcentaje de avance | H1: Estado del proyecto | I1: Riesgo del proyecto | J1: Fecha de inicio | K1: Fecha estimada de finalización | L1: Responsable
A2: PRY-001 | B2: Modernización del ERP financiero | C2: Transformación digital | D2: 850000 | E2: 396718.97 | F2: =IFERROR(E2/D2,0) -> 0.4667282 | G2: 0.49 | H2: En ejecución | I2: Alto | J2: 45887 | K2: 46055 | L2: Jefe de Desarrollo
A3: PRY-002 | B3: Implementación de gobierno de datos | C3: Gobierno de datos | D3: 3350000 | E3: 1237092.2 | F3: =IFERROR(E3/D3,0) -> 0.36928126 | G3: 0.35 | H3: En ejecución | I3: Bajo | J3: 45881 | K3: 46246 | L3: Jefe de Desarrollo
A4: PRY-003 | B4: Renovación de infraestructura de servidores | C4: Infraestructura | D4: 6100000 | E4: 1560877.8 | F4: =IFERROR(E4/D4,0) -> 0.25588161 | G4: 0.31 | H4: Atrasado | I4: Medio | J4: 45670 | K4: 45932 | L4: Jefe de Desarrollo
A5: PRY-004 | B5: Fortalecimiento del centro de monitoreo SOC | C5: Ciberseguridad | D5: 5300000 | E5: 3307949.9 | F5: =IFERROR(E5/D5,0) -> 0.62414148 | G5: 0.69 | H5: Atrasado | I5: Bajo | J5: 45703 | K5: 45932 | L5: Arquitecto Empresarial
A6: PRY-005 | B6: Automatización de gestión documental | C6: Automatización | D6: 4400000 | E6: 1301104.8 | F6: =IFERROR(E6/D6,0) -> 0.29570563 | G6: 0.34 | H6: En planificación | I6: Medio | J6: 45666 | K6: 46082 | L6: Jefe de Desarrollo
A7: PRY-006 | B7: Actualización de plataforma de respaldos | C7: Continuidad | D7: 6800000 | E7: 5895471 | F7: =IFERROR(E7/D7,0) -> 0.86698103 | G7: 0.93 | H7: En ejecución | I7: Medio | J7: 45787 | K7: 46118 | L7: Arquitecto Empresarial
A8: PRY-007 | B8: Portal de autoservicio institucional | C8: Servicios digitales | D8: 3850000 | E8: 1320528.3 | F8: =IFERROR(E8/D8,0) -> 0.34299437 | G8: 0.37 | H8: En ejecución | I8: Medio | J8: 45886 | K8: 46148 | L8: Coordinador de Gobierno TI
A9: PRY-008 | B9: Gestión de identidades y accesos | C9: Ciberseguridad | D9: 2000000 | E9: 885688.19 | F9: =IFERROR(E9/D9,0) -> 0.44284409 | G9: 0.54 | H9: Atrasado | I9: Medio | J9: 45758 | K9: 46001 | L9: Coordinador de Gobierno TI
A10: PRY-009 | B10: Migración de aplicaciones a nube híbrida | C10: Infraestructura | D10: 1900000 | E10: 1627766.6 | F10: =IFERROR(E10/D10,0) -> 0.85671925 | G10: 0.83 | H10: En ejecución | I10: Bajo | J10: 45749 | K10: 46148 | L10: Coordinador de Gobierno TI
A11: PRY-010 | B11: Modelo de arquitectura empresarial | C11: Gobierno TI | D11: 5350000 | E11: 3169570.8 | F11: =IFERROR(E11/D11,0) -> 0.59244313 | G11: 0.66 | H11: En ejecución | I11: Alto | J11: 45786 | K11: 46239 | L11: Jefe de Seguridad TI
A12: PRY-011 | B12: Catálogo de servicios TI | C12: Gestión de servicios | D12: 1950000 | E12: 726643.76 | F12: =IFERROR(E12/D12,0) -> 0.37263783 | G12: 0.44 | H12: En ejecución | I12: Bajo | J12: 45786 | K12: 46064 | L12: Coordinador de Gobierno TI
A13: PRY-012 | B13: Mejora de la red de comunicaciones | C13: Infraestructura | D13: 3500000 | E13: 1843755.3 | F13: =IFERROR(E13/D13,0) -> 0.52678724 | G13: 0.61 | H13: En ejecución | I13: Medio | J13: 45856 | K13: 46175 | L13: Coordinador de Gobierno TI
... A21: PRY-020 | B21: Repositorio de políticas y controles TI | C21: Gobierno TI | D21: 6650000 | E21: 3579553.9 | F21: =IFERROR(E21/D21,0) -> 0.53827878 | G21: 0.61 | H21: En ejecución | I21: Medio | J21: 45849 | K21: 46062 | L21: Jefe de Desarrollo

Sheet Indicadores_KPI
A1: Nombre del indicador | B1: Categoría | C1: Fórmula sugerida | D1: Meta | E1: Valor actual | F1: Semáforo | G1: Interpretación ejecutiva | H1: Sentido de la meta
A2: Nivel de madurez del gobierno de TI | B2: Gobierno TI | C2: PROMEDIO del nivel de madurez mensual | D2: 3.5 | E2: =AVERAGE(Resumen_Gobierno_TI!D2:D13) -> 3.2775 | F2: =IF(E2>=D2,"Verde",IF(E2>=D2*0.9,"Amarillo","Rojo")) -> Amarillo | G2: Evalúa la institucionalización, estandarización y mejora de las prácticas de gobierno de TI. | H2: Mayor es mejor
A3: Cumplimiento de políticas de TI | B3: Cumplimiento | C3: PROMEDIO del porcentaje mensual de cumplimiento de políticas | D3: 0.9 | E3: =AVERAGE(Resumen_Gobierno_TI!E2:E13) -> 0.85158333 | F3: =IF(E3>=D3,"Verde",IF(E3>=D3*0.9,"Amarillo","Rojo")) -> Amarillo | G3: Mide el grado de aplicación efectiva de políticas, normas y procedimientos internos. | H3: Mayor es mejor
A4: Cumplimiento normativo | B4: Cumplimiento | C4: PROMEDIO del porcentaje mensual de cumplimiento normativo | D4: 0.9 | E4: =AVERAGE(Resumen_Gobierno_TI!F2:F13) -> 0.82933333 | F4: =IF(E4>=D4,"Verde",IF(E4>=D4*0.9,"Amarillo","Rojo")) -> Amarillo | G4: Indica la alineación con requisitos regulatorios, contractuales y de auditoría. | H4: Mayor es mejor
A5: Satisfacción de usuarios | B5: Servicios TI | C5: PROMEDIO del índice mensual de satisfacción | D5: 0.85 | E5: =AVERAGE(Resumen_Gobierno_TI!G2:G13) -> 0.82766667 | F5: =IF(E5>=D5,"Verde",IF(E5>=D5*0.9,"Amarillo","Rojo")) -> Amarillo | G5: Refleja la percepción de los usuarios sobre la calidad y utilidad de los servicios tecnológicos. | H5: Mayor es mejor
A6: Riesgos críticos abiertos | B6: Riesgos TI | C6: CONTEO de riesgos críticos cuyo tratamiento no está cerrado | D6: 3 | E6: =COUNTIFS(Riesgos_TI!F2:F37,"Crítico",Riesgos_TI!H2:H37,"<>Cerrado") -> 2 | F6: =IF(E6<=D6,"Verde",IF(E6<=D6*1.2,"Amarillo","Rojo")) -> Verde | G6: Un valor alto evidencia exposición tecnológica que requiere atención ejecutiva inmediata. | H6: Menor es mejor
A7: Tiempo promedio de resolución de incidentes | B7: Gestión de incidentes | C7: PROMEDIO de horas de resolución de incidentes cerrados o resueltos | D7: 8 | E7: =AVERAGEIF(Incidentes_Servicios_TI!F2:F73,">0") -> 17.447143 | F7: =IF(E7<=D7,"Verde",IF(E7<=D7*1.2,"Amarillo","Rojo")) -> Rojo | G7: Mide la eficiencia operativa de la mesa de servicios y equipos de soporte. | H7: Menor es mejor
A8: Disponibilidad promedio de sistemas | B8: Disponibilidad | C8: PROMEDIO de disponibilidad de todos los sistemas y meses | D8: 0.995 | E8: =AVERAGE(Disponibilidad_Sistemas!E2:E73) -> 0.99710074 | F8: =IF(E8>=D8,"Verde",IF(E8>=D8*0.9,"Amarillo","Rojo")) -> Verde | G8: Resume la confiabilidad y continuidad de las plataformas tecnológicas institucionales. | H8: Mayor es mejor
A9: Cumplimiento de SLA | B9: Disponibilidad | C9: Sistemas-mes que cumplen SLA dividido entre total de mediciones | D9: 0.95 | E9: =COUNTIF(Disponibilidad_Sistemas!H2:H73,"Cumple")/COUNTA(Disponibilidad_Sistemas!H2:H73) -> 0.58333333 | F9: =IF(E9>=D9,"Verde",IF(E9>=D9*0.9,"Amarillo","Rojo")) -> Rojo | G9: Indica el porcentaje de compromisos de nivel de servicio alcanzados. | H9: Mayor es mejor
A10: Porcentaje de auditorías cerradas | B10: Auditoría TI | C10: Auditorías con plan de acción cerrado dividido entre total de auditorías | D10: 0.7 | E10: =COUNTIF(Auditorias_TI!H2:H19,"Cerrado")/COUNTA(Auditorias_TI!A2:A19) -> 0.27777778 | F10: =IF(E10>=D10,"Verde",IF(E10>=D10*0.9,"Amarillo","Rojo")) -> Rojo | G10: Evalúa la capacidad de remediar hallazgos y cerrar compromisos de auditoría. | H10: Mayor es mejor
A11: Avance promedio de proyectos tecnológicos | B11: Portafolio TI | C11: PROMEDIO del porcentaje de avance de los proyectos | D11: 0.65 | E11: =AVERAGE(Proyectos_TI!G2:G21) -> 0.5525 | F11: =IF(E11>=D11,"Verde",IF(E11>=D11*0.9,"Amarillo","Rojo")) -> Rojo | G11: Muestra el progreso agregado del portafolio de iniciativas tecnológicas. | H11: Mayor es mejor
A12: Ejecución presupuestaria de proyectos TI | B12: Portafolio TI | C12: Presupuesto ejecutado total dividido entre presupuesto aprobado total | D12: 0.85 | E12: =SUM(Proyectos_TI!E2:E21)/SUM(Proyectos_TI!D2:D21) -> 0.54419561 | F12: =IF(E12>=D12,"Verde",IF(E12>=D12*0.9,"Amarillo","Rojo")) -> Rojo | G12: Permite evaluar la utilización de recursos financieros destinados al portafolio tecnológico. | H12: Mayor es mejor
A13: Proyectos con riesgo alto | B13: Portafolio TI | C13: CONTEO de proyectos clasificados con riesgo alto | D13: 4 | E13: =COUNTIF(Proyectos_TI!I2:I21,"Alto") -> 5 | F13: =IF(E13<=D13,"Verde",IF(E13<=D13*1.2,"Amarillo","Rojo")) -> Rojo | G13: Identifica la concentración de iniciativas que requieren seguimiento ejecutivo reforzado. | H13: Menor es mejor
A14: Índice general de gobierno de SI | B14: Gobierno TI | C14: Promedio compuesto de políticas, normativa, satisfacción y madurez normalizada | D14: 0.85 | E14: =(AVERAGE(Resumen_Gobierno_TI!E2:E13)+AVERAGE(Resumen_Gobierno_TI!F2:F13)+AVERAGE(Resumen_Gobierno_TI!G2:G13)+(AVERAGE(Resumen_Gobierno_TI!D2:D13)/5))/4 -> 0.79102083 | F14: =IF(E14>=D14,"Verde",IF(E14>=D14*0.9,"Amarillo","Rojo")) -> Amarillo | G14: Sintetiza la condición general del gobierno de sistemas de información en una escala de 0 a 100%. | H14: Mayor es mejor

Sheet Diccionario_Datos
A1: Hoja | B1: Columna | C1: Significado | D1: Tipo de dato | E1: Utilidad para análisis e indicadores | F1: Ejemplo de valor
A2: Resumen_Gobierno_TI | B2: Mes | C2: Mes de referencia del indicador agregado. | D2: Texto | E2: Permite analizar tendencias y filtrar periodos. | F2: Enero
A3: Resumen_Gobierno_TI | B3: Año | C3: Año calendario de la medición. | D3: Entero | E3: Facilita comparaciones interanuales. | F3: 2025
A4: Resumen_Gobierno_TI | B4: Área responsable | C4: Unidad responsable de consolidar el gobierno de TI. | D4: Texto | E4: Permite segmentar responsabilidades. | F4: Oficina de Gobierno TI
A5: Resumen_Gobierno_TI | B5: Nivel de madurez de gobierno de TI | C5: Valor de madurez en escala de 1 a 5. | D5: Decimal | E5: Mide evolución de capacidades y prácticas. | F5: 3.25
A6: Resumen_Gobierno_TI | B6: Porcentaje de cumplimiento de políticas | C6: Grado de aplicación de políticas internas. | D6: Porcentaje | E6: Sirve para semáforos y tendencias de cumplimiento. | F6: 84.2%
A7: Resumen_Gobierno_TI | B7: Porcentaje de cumplimiento normativo | C7: Alineación con requisitos regulatorios y de control. | D7: Porcentaje | E7: Permite identificar brechas normativas. | F7: 82.1%
A8: Resumen_Gobierno_TI | B8: Índice de satisfacción de usuarios | C8: Percepción de usuarios sobre servicios TI. | D8: Porcentaje | E8: Mide calidad percibida y experiencia de servicio. | F8: 82.3%
A9: Resumen_Gobierno_TI | B9: Estado general del gobierno de TI | C9: Clasificación ejecutiva derivada de los indicadores. | D9: Texto calculado | E9: Resume la condición del periodo. | F9: Controlado
A10: Riesgos_TI | B10: ID del riesgo | C10: Identificador único del riesgo tecnológico. | D10: Texto | E10: Permite trazabilidad y conteo de riesgos. | F10: R-001
A11: Riesgos_TI | B11: Categoría del riesgo | C11: Clasificación temática del riesgo. | D11: Texto | E11: Facilita análisis por tipo de exposición. | F11: Ciberseguridad
A12: Riesgos_TI | B12: Descripción del riesgo | C12: Evento potencial y su posible consecuencia. | D12: Texto | E12: Aporta contexto para análisis cualitativo. | F12: Acceso no autorizado...
... A68: Indicadores_KPI | B68: Sentido de la meta | C68: Indica si un valor mayor o menor es favorable. | D68: Texto | E68: Permite aplicar reglas de semáforo. | F68: Mayor es mejor

Sheet Recomendaciones_Dashboard
A1: Componente | B1: Objetivo ejecutivo | C1: Visualización sugerida | D1: Fuente de datos | E1: Filtro o dimensión | F1: Recomendación de diseño
A2: Tarjeta KPI | B2: Mostrar el nivel promedio de madurez de gobierno TI. | C2: Tarjeta con valor y variación | D2: Resumen_Gobierno_TI | E2: Año y mes | F2: Escala 1–5; mostrar meta y tendencia.
A3: Tarjeta KPI | B3: Visualizar cumplimiento de políticas. | C3: Tarjeta porcentual con semáforo | D3: Indicadores_KPI | E3: Mes | F3: Verde ≥ 90%, amarillo 81–89%, rojo < 81%.
A4: Tarjeta KPI | B4: Visualizar cumplimiento normativo. | C4: Tarjeta porcentual con semáforo | D4: Indicadores_KPI | E4: Mes | F4: Incluir comparación contra la meta institucional.
A5: Tarjeta KPI | B5: Mostrar riesgos críticos abiertos. | C5: Tarjeta de alerta | D5: Riesgos_TI | E5: Área y estado | F5: Usar énfasis visual cuando supere la tolerancia.
A6: Tarjeta KPI | B6: Mostrar tiempo promedio de resolución. | C6: Tarjeta numérica en horas | D6: Incidentes_Servicios_TI | E6: Prioridad y servicio | F6: Agregar variación respecto al periodo anterior.
A7: Tarjeta KPI | B7: Mostrar disponibilidad promedio. | C7: Tarjeta porcentual | D7: Disponibilidad_Sistemas | E7: Sistema y mes | F7: Usar tres decimales por la sensibilidad del SLA.
A8: Gráfico de líneas | B8: Analizar evolución de madurez, políticas, normativa y satisfacción. | C8: Líneas múltiples por mes | D8: Resumen_Gobierno_TI | E8: Año | F8: Normalizar la madurez o usar eje secundario.
A9: Gráfico de barras | B9: Comparar riesgos por categoría y nivel. | C9: Barras apiladas | D9: Riesgos_TI | E9: Área, nivel y estado | F9: Ordenar de mayor a menor exposición.
A10: Gráfico circular | B10: Mostrar distribución de incidentes por prioridad. | C10: Dona o pastel | D10: Incidentes_Servicios_TI | E10: Mes y servicio | F10: Limitar a cuatro categorías para legibilidad.
A11: Gráfico de barras | B11: Comparar MTTR por servicio afectado. | C11: Barras horizontales | D11: Incidentes_Servicios_TI | E11: Prioridad y estado | F11: Agregar línea de meta de 8 horas.
A12: Mapa de calor | B12: Identificar sistemas y meses con menor disponibilidad. | C12: Matriz sistema versus mes | D12: Disponibilidad_Sistemas | E12: Sistema y año | F12: Formato condicional rojo-amarillo-verde.
... A21: Diseño general | B21: Mantener una lectura profesional y académica. | C21: Distribución en cuadrícula | D21: Todas las hojas | E21: Todos | F21: Usar azul institucional, espacios en blanco y máximo 6 visuales por vista.

Sheet Vista_Ejecutiva
A1: GOBIERNO DE SISTEMAS DE INFORMACIÓN — VISTA EJECUTIVA
A3: Datos simulados para dashboard académico | Autor: Jeffrey Dennis Coello Medina | Periodo: enero–diciembre 2025
A5: Madurez promedio | D5: Cumplimiento de políticas | G5: Riesgos críticos abiertos | J5: Disponibilidad promedio
A6: =Indicadores_KPI!E2 -> 3.2775 | D6: =Indicadores_KPI!E3 -> 0.85158333 | G6: =Indicadores_KPI!E6 -> 2 | J6: =Indicadores_KPI!E8 -> 0.99710074
A10: Satisfacción de usuarios | D10: Resolución promedio (horas) | G10: Auditorías cerradas | J10: Índice general de gobierno SI
A11: =Indicadores_KPI!E5 -> 0.82766667 | D11: =Indicadores_KPI!E7 -> 17.447143 | G11: =Indicadores_KPI!E10 -> 0.27777778 | J11: =Indicadores_KPI!E14 -> 0.79102083
A16: Mes | B16: Madurez | C16: Cumplimiento políticas | D16: Cumplimiento normativo | E16: Satisfacción usuarios
A17: =Resumen_Gobierno_TI!A2 -> Enero | B17: =Resumen_Gobierno_TI!D2 -> 2.85 | C17: =Resumen_Gobierno_TI!E2 -> 0.781 | D17: =Resumen_Gobierno_TI!F2 -> 0.752 | E17: =Resumen_Gobierno_TI!G2 -> 0.768
A18: =Resumen_Gobierno_TI!A3 -> Febrero | B18: =Resumen_Gobierno_TI!D3 -> 2.92 | C18: =Resumen_Gobierno_TI!E3 -> 0.796 | D18: =Resumen_Gobierno_TI!F3 -> 0.769 | E18: =Resumen_Gobierno_TI!G3 -> 0.776
A19: =Resumen_Gobierno_TI!A4 -> Marzo | B19: =Resumen_Gobierno_TI!D4 -> 3.02 | C19: =Resumen_Gobierno_TI!E4 -> 0.804 | D19: =Resumen_Gobierno_TI!F4 -> 0.781 | E19: =Resumen_Gobierno_TI!G4 -> 0.789
A20: =Resumen_Gobierno_TI!A5 -> Abril | B20: =Resumen_Gobierno_TI!D5 -> 3.08 | C20: =Resumen_Gobierno_TI!E5 -> 0.816 | D20: =Resumen_Gobierno_TI!F5 -> 0.793 | E20: =Resumen_Gobierno_TI!G5 -> 0.801
A21: =Resumen_Gobierno_TI!A6 -> Mayo | B21: =Resumen_Gobierno_TI!D6 -> 3.16 | C21: =Resumen_Gobierno_TI!E6 -> 0.831 | D21: =Resumen_Gobierno_TI!F6 -> 0.807 | E21: =Resumen_Gobierno_TI!G6 -> 0.812
A22: =Resumen_Gobierno_TI!A7 -> Junio | B22: =Resumen_Gobierno_TI!D7 -> 3.25 | C22: =Resumen_Gobierno_TI!E7 -> 0.842 | D22: =Resumen_Gobierno_TI!F7 -> 0.821 | E22: =Resumen_Gobierno_TI!G7 -> 0.823
A23: =Resumen_Gobierno_TI!A8 -> Julio | B23: =Resumen_Gobierno_TI!D8 -> 3.31 | C23: =Resumen_Gobierno_TI!E8 -> 0.854 | D23: =Resumen_Gobierno_TI!F8 -> 0.835 | E23: =Resumen_Gobierno_TI!G8 -> 0.831
A24: =Resumen_Gobierno_TI!A9 -> Agosto | B24: =Resumen_Gobierno_TI!D9 -> 3.38 | C24: =Resumen_Gobierno_TI!E9 -> 0.866 | D24: =Resumen_Gobierno_TI!F9 -> 0.848 | E24: =Resumen_Gobierno_TI!G9 -> 0.842
A25: =Resumen_Gobierno_TI!A10 -> Septiembre | B25: =Resumen_Gobierno_TI!D10 -> 3.46 | C25: =Resumen_Gobierno_TI!E10 -> 0.881 | D25: =Resumen_Gobierno_TI!F10 -> 0.862 | E25: =Resumen_Gobierno_TI!G10 -> 0.854
A26: =Resumen_Gobierno_TI!A11 -> Octubre | B26: =Resumen_Gobierno_TI!D11 -> 3.55 | C26: =Resumen_Gobierno_TI!E11 -> 0.896 | D26: =Resumen_Gobierno_TI!F11 -> 0.877 | E26: =Resumen_Gobierno_TI!G11 -> 0.866
A27: =Resumen_Gobierno_TI!A12 -> Noviembre | B27: =Resumen_Gobierno_TI!D12 -> 3.63 | C27: =Resumen_Gobierno_TI!E12 -> 0.918 | D27: =Resumen_Gobierno_TI!F12 -> 0.895 | E27: =Resumen_Gobierno_TI!G12 -> 0.879
A28: =Resumen_Gobierno_TI!A13 -> Diciembre | B28: =Resumen_Gobierno_TI!D13 -> 3.72 | C28: =Resumen_Gobierno_TI!E13 -> 0.934 | D28: =Resumen_Gobierno_TI!F13 -> 0.912 | E28: =Resumen_Gobierno_TI!G13 -> 0.891
A31: LECTURA EJECUTIVA RECOMENDADA
A32: 1) Revise primero el índice general, los riesgos críticos y la disponibilidad. 2) Analice la tendencia mensual de madurez, políticas, normativa y satisfacción. 3) Profundice en las hojas operativas mediante filtros por área, sistema, prioridad, riesgo y estado. 4) Use Indicadores_KPI como capa semántica para Power BI, Excel o un dashboard HTML.
